soilspectfm/__init__.py
soilspectfm/_modidx.py
soilspectfm/core.py
soilspectfm/utils.py
soilspectfm/visualization.py
soilspectfm-0.0.5.dist-info/LICENSE
soilspectfm-0.0.5.dist-info/METADATA
soilspectfm-0.0.5.dist-info/WHEEL
soilspectfm-0.0.5.dist-info/entry_points.txt
soilspectfm-0.0.5.dist-info/top_level.txt
soilspectfm-0.0.5.dist-info/RECORD
