Metadata-Version: 2.2
Name: soilspectfm
Version: 0.0.5
Summary: Soil infrared spectra preprocessing utilities
Home-page: https://github.com/franckalbinet/soilspectfm
Author: Franck Albinet
Author-email: franckalbinet@gmail.com
License: Apache Software License 2.0
Keywords: nbdev jupyter notebook python
Classifier: Development Status :: 4 - Beta
Classifier: Intended Audience :: Developers
Classifier: Natural Language :: English
Classifier: Programming Language :: Python :: 3.7
Classifier: Programming Language :: Python :: 3.8
Classifier: Programming Language :: Python :: 3.9
Classifier: Programming Language :: Python :: 3.10
Classifier: Programming Language :: Python :: 3.11
Classifier: Programming Language :: Python :: 3.12
Classifier: License :: OSI Approved :: Apache Software License
Requires-Python: >=3.7
License-File: LICENSE
Requires-Dist: fastcore
Requires-Dist: scikit-learn
Requires-Dist: matplotlib
Requires-Dist: PyWavelets
Provides-Extra: dev
Requires-Dist: soilspecdata; extra == "dev"
Requires-Dist: nbdev; extra == "dev"
Requires-Dist: ipykernel; extra == "dev"
Dynamic: author
Dynamic: author-email
Dynamic: classifier
Dynamic: description
Dynamic: description-content-type
Dynamic: home-page
Dynamic: keywords
Dynamic: license
Dynamic: provides-extra
Dynamic: requires-dist
Dynamic: requires-python
Dynamic: summary
